Workbook

Sheet Sheet5
A3: Row Labels | B3: Sum of Sales | C3: Sum of Profit | G3: South Profit Margin
A4: UltraNote 15 | B4: 62129132 | C4: 12016439 | G4: GETPIVOTDATA("Sum of Cost",$A$3,"Region","East")
A5: ProBook X | B5: 52738378 | C5: 10106128
A6: Pixel Max | B6: 36908904 | C6: 7270542.2
A7: Galaxy Pro | B7: 35085861 | C7: 6750345.7
A8: AeroBook 14 | B8: 34658947 | C8: 6576636.6
A9: OnePlus Nord | B9: 20417956 | C9: 3937721.7
A10: Meeting Table | B10: 16521766 | C10: 3163388
A11: Office Table | B11: 9441467.7 | C11: 1864852.2
A12: Executive Chair | B12: 9480772.5 | C12: 1762886.5
A13: Ergo Chair | B13: 6245393.5 | C13: 1193929.1
A14: Grand Total | B14: 2.8362858e+08 | C14: 54642869

Sheet Sheet7

Sheet Sheet8
A3: Row Labels | B3: Sum of Sales | C3: Sum of Profit | D3: Sum of Quantity | E3: Sum of Discount Profit Margin
A4: 0 | B4: 63248584 | C4: 12324913 | D4: 4014 | E4: 0.19486465
A5: 0.05 | B5: 77569818 | C5: 15106380 | D5: 5180 | E5: 0.19474558
A6: 0.1 | B6: 98280692 | C6: 18676637 | D6: 6557 | E6: 0.19003363
A7: 0.15 | B7: 52553320 | C7: 10100844 | D7: 3728 | E7: 0.19220182
A8: 0.2 | B8: 17225786 | C8: 3214418.3 | D8: 1432 | E8: 0.18660503
A9: 0.25 | B9: 7387716.9 | C9: 1446310.7 | D9: 731 | E9: 0.19577235
A10: Grand Total | B10: 3.1626592e+08 | C10: 60869502 | D10: 21642 | E10: 0.19246305

Sheet Sheet9
A3: Row Labels | B3: Sum of Sales | C3: Sum of Profit | D3: Sales Growth | E3: Porfit Growth
A4: 2024 | B4: 1.538534e+08 | C4: 29967249 | D4: =(162412519.61-153853397.43)/153853397.43 -> 0.055631675 | E4: =(30902252.89-29967248.99)/29967248.99 -> 0.031200859
A5: Qtr1 | B5: 33094442 | C5: 6548408.1
A6: Jan | B6: 10638923 | C6: 2218453.8
A7: Feb | B7: 11154200 | C7: 2155723.5
A8: Mar | B8: 11301318 | C8: 2174230.8
A9: Qtr2 | B9: 42385217 | C9: 8168562.9
A10: Apr | B10: 16067880 | C10: 3113199.2
A11: May | B11: 13756310 | C11: 2631242.5
A12: Jun | B12: 12561026 | C12: 2424121.2
A13: Qtr3 | B13: 39738908 | C13: 7663261.8
A14: Jul | B14: 13046865 | C14: 2464120.7
A15: Aug | B15: 15357900 | C15: 2917895.8
A16: Sep | B16: 11334143 | C16: 2281245.3
... A38: Grand Total | B38: 3.1626592e+08 | C38: 60869502

Sheet Sheet1
A3: Row Labels | B3: Sum of Sales | C3: Sum of Profit
A4: Aarav Sharma | B4: 4554546.1 | C4: 786475.23
A5: Ananya Reddy | B5: 4881119.6 | C5: 1020043
A6: Ishaan Rao | B6: 4791309.5 | C6: 1020255.3
A7: Meera Reddy | B7: 4303014.3 | C7: 794294.49
A8: Nisha Sharma | B8: 4218591.5 | C8: 717155.04
A9: Priya Kumar | B9: 4356758 | C9: 812630.78
A10: Rahul Sharma | B10: 4367859.5 | C10: 889174.56
A11: Rahul Verma | B11: 4711388.4 | C11: 893884.51
A12: Sneha Kumar | B12: 4713088.1 | C12: 879727.66
A13: Sneha Rao | B13: 4431615.8 | C13: 849804.95
A14: Grand Total | B14: 45329291 | C14: 8663445.4

Sheet Raw_Sales_Data
A1: Order_ID | B1: Order_Date | C1: Customer_ID | D1: Customer_Name | E1: Region | F1: State | G1: Category | H1: Sub_Category | I1: Product | J1: Quantity | K1: Unit_Price | L1: Discount | M1: Sales | N1: Cost | O1: Profit | Q1: Total Sales | R1: Clean_Region
A2: ORD-100001 | B2: 45590 | C2: CUST-1748 | D2: Ishaan Singh | E2: West | F2: Goa | G2: Technology | H2: Phones | I2: OnePlus Nord | J2: 2 | K2: 24303.55 | L2: 0.1 | M2: 43746.39 | N2: 37178.88 | O2: 6567.51 | P2: =COUNTA(A:A,-1) -> 7002 | Q2: =SUM($M:$M) -> 3.1626592e+08 | R2: =PROPER(TRIM(E2)) -> West
A3: ORD-100002 | B3: 45717 | C3: CUST-1554 | D3: Ananya Kumar | E3: East | F3: West Bengal | G3: Furniture | H3: Chairs | I3: Ergo Chair | J3: 5 | K3: 10053.37 | L3: 0.05 | M3: 47753.51 | N3: 36562.21 | O3: 11191.3 | P3: =COUNTA(A:A)-1 -> 7000 | Q3: Total Profit | R3: =PROPER(TRIM(E3)) -> East
A4: ORD-100003 | B4: 45757 | C4: CUST-1448 | D4: Priya Reddy | E4: North | F4: Haryana | G4: Technology | H4: Accessories | I4: Mechanical Keyboard | J4: 1 | K4: 2465.17 | L4: 0.05 | M4: 2341.91 | N4: 1819.35 | O4: 522.56 | P4: =COUNTIF($A:$A,A2) -> 1 | Q4: =SUM($O:$O) -> 60869502 | R4: =PROPER(TRIM(E4)) -> North
A5: ORD-100004 | B5: 45966 | C5: CUST-1396 | D5: Arjun Sharma | E5: North | F5: Haryana | G5: Furniture | H5: Chairs | I5: Mesh Chair | J5: 2 | K5: 4899.22 | L5: 0.1 | M5: 8818.6 | N5: 7475.38 | O5: 1343.22 | P5: =COUNTBLANK(D2:D7000) -> 0 | Q5: Orders | R5: =PROPER(TRIM(E5)) -> North
A6: ORD-100005 | B6: 45458 | C6: CUST-1392 | D6: Aditya Patel | E6: South | F6: Telangana | G6: Furniture | H6: Tables | I6: Office Table | J6: 2 | K6: 12557.81 | L6: 0.05 | M6: 23859.84 | N6: 18386.5 | O6: 5473.34 | P6: =COUNTBLANK(F2:F7000) -> 0 | Q6: =COUNTA($A:$A)-1 -> 7000 | R6: =PROPER(TRIM(E6)) -> South
A7: ORD-100006 | B7: 45322 | C7: CUST-1693 | D7: Ananya Verma | E7: South | F7: Kerala | G7: Office Supplies | H7: Paper | I7: A4 Copy Paper | J7: 5 | K7: 371.3 | L7: 0.15 | M7: 1578.02 | N7: 1328.97 | O7: 249.05 | P7: =COUNTBLANK(L2:L7001) -> 0 | Q7: Quantity Sold | R7: =PROPER(TRIM(E7)) -> South
A8: ORD-100007 | B8: 45401 | C8: CUST-1328 | D8: Ishaan Rao | E8: South | F8: Tamil Nadu | G8: Technology | H8: Phones | I8: OnePlus Nord | J8: 5 | K8: 25700.11 | L8: 0.1 | M8: 115650.5 | N8: 89072.06 | O8: 26578.44 | Q8: =SUM($J:$J) -> 21642 | R8: =PROPER(TRIM(E8)) -> South
A9: ORD-100008 | B9: 45937 | C9: CUST-1239 | D9: Aarav Kumar | E9: East | F9: West Bengal | G9: Office Supplies | H9: Binders | I9: Document Folder | J9: 1 | K9: 129.01 | L9: 0.1 | M9: 116.11 | N9: 85.95 | O9: 30.16 | Q9: Average Order Value | R9: =PROPER(TRIM(E9)) -> East
A10: ORD-100009 | B10: 45918 | C10: CUST-1732 | D10: Sneha Singh | E10: North | F10: Uttarakhand | G10: Office Supplies | H10: Paper | I10: A4 Copy Paper | J10: 1 | K10: 473.87 | L10: 0.1 | M10: 426.48 | N10: 351.04 | O10: 75.44 | Q10: =AVERAGE(Q2/Q6) -> 45180.845 | R10: =PROPER(TRIM(E10)) -> North
A11: ORD-100010 | B11: 45875 | C11: CUST-1570 | D11: Meera Patel | E11: North | F11: Haryana | G11: Office Supplies | H11: Binders | I11: Ring Binder | J11: 1 | K11: 308.69 | L11: 0.05 | M11: 293.26 | N11: 256.56 | O11: 36.7 | Q11: =COUNTA(_xlfn.UNIQUE(Raw_Sales_Data!C2:C7001)) -> 800 | R11: =PROPER(TRIM(E11)) -> North
A12: ORD-100011 | B12: 45309 | C12: CUST-1043 | D12: Ananya Patel | E12: South | F12: Kerala | G12: Office Supplies | H12: Stationery | I12: Notebook Pack | J12: 2 | K12: 444.12 | L12: 0.15 | M12: 755 | N12: 581.43 | O12: 173.57 | R12: =PROPER(TRIM(E12)) -> South
A13: ORD-100012 | B13: 45493 | C13: CUST-1207 | D13: Aditya Reddy | E13: East | F13: Jharkhand | G13: Technology | H13: Accessories | I13: Mechanical Keyboard | J13: 3 | K13: 2009.93 | L13: 0.05 | M13: 5728.3 | N13: 4829.1 | O13: 899.2 | P13: =COUNTIFS(A2:A7001,"<>",E2:E7001,"") -> 0 | R13: =PROPER(TRIM(E13)) -> East
A14: ORD-100013 | B14: 45637 | C14: CUST-1204 | D14: Rohan Rao | E14: East | F14: Jharkhand | G14: Office Supplies | H14: Paper | I14: A4 Copy Paper | J14: 1 | K14: 289.44 | L14: 0.15 | M14: 246.02 | N14: 189.89 | O14: 56.13 | R14: =PROPER(TRIM(E14)) -> East
A15: ORD-100014 | B15: 45920 | C15: CUST-1707 | D15: Sneha Reddy | E15: South | F15: Kerala | G15: Technology | H15: Accessories | I15: USB-C Hub | J15: 1 | K15: 1431.12 | L15: 0 | M15: 1431.12 | N15: 1157.31 | O15: 273.81 | R15: =PROPER(TRIM(E15)) -> South
A16: ORD-100015 | B16: 45396 | C16: CUST-1787 | D16: Ananya Kumar | E16: South | F16: Tamil Nadu | G16: Furniture | H16: Storage | I16: Bookshelf | J16: 2 | K16: 7418.25 | L16: 0.05 | M16: 14094.68 | N16: 11855.09 | O16: 2239.59 | R16: =PROPER(TRIM(E16)) -> South
A17: ORD-100016 | B17: 45554 | C17: CUST-1006 | D17: Nisha Rao | E17: South | F17: Telangana | G17: Office Supplies | H17: Stationery | I17: Notebook Pack | J17: 3 | K17: 316.53 | L17: 0.2 | M17: 759.67 | N17: 581.41 | O17: 178.26 | R17: =PROPER(TRIM(E17)) -> South
A18: ORD-100017 | B18: 45977 | C18: CUST-1335 | D18: Rohan Verma | E18: West | F18: Gujarat | G18: Technology | H18: Laptops | I18: AeroBook 14 | J18: 6 | K18: 48731.28 | L18: 0.05 | M18: 277768.3 | N18: 245426.18 | O18: 32342.12 | R18: =PROPER(TRIM(E18)) -> West
A19: ORD-100018 | B19: 45599 | C19: CUST-1654 | D19: Sneha Rao | E19: West | F19: Maharashtra | G19: Technology | H19: Laptops | I19: AeroBook 14 | J19: 1 | K19: 48464.07 | L19: 0.1 | M19: 43617.66 | N19: 32684.4 | O19: 10933.26 | R19: =PROPER(TRIM(E19)) -> West
A20: ORD-100019 | B20: 45872 | C20: CUST-1224 | D20: Meera Kumar | E20: West | F20: Gujarat | G20: Technology | H20: Accessories | I20: Mechanical Keyboard | J20: 2 | K20: 3958.98 | L20: 0.15 | M20: 6730.27 | N20: 5695.45 | O20: 1034.82 | R20: =PROPER(TRIM(E20)) -> West
A21: ORD-100020 | B21: 45362 | C21: CUST-1273 | D21: Vikram Patel | E21: South | F21: Andhra Pradesh | G21: Office Supplies | H21: Paper | I21: Legal Paper | J21: 2 | K21: 738.61 | L21: 0.05 | M21: 1403.36 | N21: 1222.21 | O21: 181.15 | R21: =PROPER(TRIM(E21)) -> South
A22: ORD-100021 | B22: 45961 | C22: CUST-1663 | D22: Rahul Rao | E22: North | F22: Haryana | G22: Office Supplies | H22: Paper | I22: A4 Copy Paper | J22: 2 | K22: 381.65 | L22: 0.05 | M22: 725.13 | N22: 629.35 | O22: 95.78 | R22: =PROPER(TRIM(E22)) -> North
A23: ORD-100022 | B23: 45312 | C23: CUST-1257 | D23: Aarav Patel | E23: South | F23: Kerala | G23: Office Supplies | H23: Paper | I23: Legal Paper | J23: 6 | K23: 606.03 | L23: 0 | M23: 3636.18 | N23: 3108.69 | O23: 527.49 | R23: =PROPER(TRIM(E23)) -> South
A24: ORD-100023 | B24: 45809 | C24: CUST-1629 | D24: Kavya Rao | E24: South | F24: Telangana | G24: Furniture | H24: Tables | I24: Meeting Table | J24: 4 | K24: 21451.77 | L24: 0.1 | M24: 77226.37 | N24: 55923.66 | O24: 21302.71 | R24: =PROPER(TRIM(E24)) -> South
A25: ORD-100024 | B25: 46002 | C25: CUST-1372 | D25: Arjun Reddy | E25: West | F25: Madhya Pradesh | G25: Technology | H25: Accessories | I25: Wireless Mouse | J25: 8 | K25: 1037.74 | L25: 0.15 | M25: 7056.63 | N25: 5739.94 | O25: 1316.69 | R25: =PROPER(TRIM(E25)) -> West
... A6999: ORD-106998 | B6999: 45964 | C6999: CUST-1435 | D6999: Nisha Reddy | E6999: East | F6999: Assam | G6999: Furniture | H6999: Storage | I6999: Filing Cabinet | J6999: 4 | K6999: 6938.21 | L6999: 0.05 | M6999: 26365.2 | N6999: 19916.79 | O6999: 6448.41 | R6999: =PROPER(TRIM(E6999)) -> East
A7000: ORD-106999 | B7000: 45566 | C7000: CUST-1745 | D7000: Ishaan Kumar | E7000: West | F7000: Maharashtra | G7000: Technology | H7000: Phones | I7000: OnePlus Nord | J7000: 3 | K7000: 32890.38 | L7000: 0.05 | M7000: 93737.58 | N7000: 75457.46 | O7000: 18280.12
A7001: ORD-107000 | B7001: 45709 | C7001: CUST-1699 | D7001: Meera Patel | E7001: North | F7001: Uttarakhand | G7001: Furniture | H7001: Chairs | I7001: Executive Chair | J7001: 3 | K7001: 16984.24 | L7001: 0.05 | M7001: 48405.08 | N7001: 42788.22 | O7001: 5616.86

Sheet Sales Dashboard
A1: SALES PERFORMANCE DASHBOARD
A3: Total Sales | C3: Total Profits | E3: Total Orders | G3: Quantity Sold | I3: Average Order Value
A6: =SUM(Raw_Sales_Data!M2:M7001) -> 3.1626592e+08

Sheet Sheet6
A1: Clean_Region
A2: =PROPER(TRIM(Raw_Sales_Data!E2)) -> West | B2: {=_xlfn.UNIQUE(A$2:A$1048576)} -> West
A3: =PROPER(TRIM(Raw_Sales_Data!E3)) -> East | B3: East
A4: =PROPER(TRIM(Raw_Sales_Data!E4)) -> North | B4: North
A5: =PROPER(TRIM(Raw_Sales_Data!E5)) -> North | B5: South
A6: =PROPER(TRIM(Raw_Sales_Data!E6)) -> South | B6: 0
A7: =PROPER(TRIM(Raw_Sales_Data!E7)) -> South
A8: =PROPER(TRIM(Raw_Sales_Data!E8)) -> South
A9: =PROPER(TRIM(Raw_Sales_Data!E9)) -> East
A10: =PROPER(TRIM(Raw_Sales_Data!E10)) -> North
A11: =PROPER(TRIM(Raw_Sales_Data!E11)) -> North
A12: =PROPER(TRIM(Raw_Sales_Data!E12)) -> South
A13: =PROPER(TRIM(Raw_Sales_Data!E13)) -> East
A14: =PROPER(TRIM(Raw_Sales_Data!E14)) -> East
A15: =PROPER(TRIM(Raw_Sales_Data!E15)) -> South
A16: =PROPER(TRIM(Raw_Sales_Data!E16)) -> South
A17: =PROPER(TRIM(Raw_Sales_Data!E17)) -> South
A18: =PROPER(TRIM(Raw_Sales_Data!E18)) -> West
... A7001: =PROPER(TRIM(Raw_Sales_Data!E7001)) -> North

Sheet Project_Info
A1: Project | B1: Purpose | C1: Rows | D1: Note
A2: Sales Performance & Business Insights Dashboard | B2: Practice end-to-end Data Analyst workflow using Excel, MySQL and later Power BI. | C2: 7005 | D2: Raw data intentionally contains a small number of duplicates, missing values and text inconsistencies for the cleaning stage.
